backports-stubs/METADATA.toml
backports-stubs/__init__.pyi
backports-stubs/ssl_match_hostname.pyi
types_backports-0.1.3.dist-info/METADATA
types_backports-0.1.3.dist-info/WHEEL
types_backports-0.1.3.dist-info/top_level.txt
types_backports-0.1.3.dist-info/RECORD
