Metadata-Version: 2.1
Name: types-backports
Version: 0.1.3
Summary: Typing stubs for backports
Home-page: https://github.com/python/typeshed
License: Apache-2.0 license
Platform: UNKNOWN
Classifier: License :: OSI Approved :: Apache Software License
Classifier: Typing :: Typed
